sunson/SunSon.py
sunson/__init__.py
sunson/__version__.py
sunson-1.0.3.dist-info/DESCRIPTION.rst
sunson-1.0.3.dist-info/METADATA
sunson-1.0.3.dist-info/RECORD
sunson-1.0.3.dist-info/WHEEL
sunson-1.0.3.dist-info/metadata.json
sunson-1.0.3.dist-info/top_level.txt
